min_llm_server_client/__init__.py
min_llm_server_client/api_server.py
min_llm_server_client-0.3.9.dist-info/licenses/LICENSE-2.0.txt
min_llm_server_client-0.3.9.dist-info/METADATA
min_llm_server_client-0.3.9.dist-info/WHEEL
min_llm_server_client-0.3.9.dist-info/entry_points.txt
min_llm_server_client-0.3.9.dist-info/top_level.txt
min_llm_server_client-0.3.9.dist-info/RECORD
