Metadata-Version: 2.4
Name: min-llm-server-client
Version: 0.3.9
Summary: A minimal Flask API server for local HuggingFace LLMs
Author: Afshin Sadeghi
Author-email: Afshin Sadeghi <sadeghi.afshin@gmail.com>
License-Expression: Apache-2.0
Requires-Python: >=3.6
License-File: LICENSE-2.0.txt
Requires-Dist: transformers>=4.40.0
Requires-Dist: accelerate>=0.28.0
Requires-Dist: torch
Requires-Dist: flask
Requires-Dist: sentencepiece
Requires-Dist: pynvml
Dynamic: author
Dynamic: license-file
Dynamic: requires-python
